kriging/__init__.py
kriging/_kriging.py
kriging/_plotting.py
kriging/base.py
kriging/data/mapdata.json
kriging-0.0.1.dist-info/LICENSE
kriging-0.0.1.dist-info/METADATA
kriging-0.0.1.dist-info/WHEEL
kriging-0.0.1.dist-info/top_level.txt
kriging-0.0.1.dist-info/RECORD
