Metadata-Version: 2.1
Name: kriging
Version: 0.0.1
Summary: Ordinary Kriging Interpolation
Home-page: UNKNOWN
Author: Erssle
Author-email: ersslee@gmail.com
License: UNKNOWN
Platform: UNKNOWN
Classifier: Programming Language :: Python :: 3
Classifier: License :: OSI Approved :: MIT License
Classifier: Operating System :: OS Independent
Requires-Python: >=3.6
Requires-Dist: numpy
Requires-Dist: shapely
Requires-Dist: matplotlib
